mdprint/__init__.py
mdprint/helper_functions.py
mdprint/mdprint_functions.py
mdprint-0.2.0.dist-info/LICENCE
mdprint-0.2.0.dist-info/METADATA
mdprint-0.2.0.dist-info/WHEEL
mdprint-0.2.0.dist-info/top_level.txt
mdprint-0.2.0.dist-info/RECORD
