Metadata-Version: 2.1
Name: mdprint
Version: 0.2.0
Summary: Python tools to print strings to markdown file with styles. Also allows printing dicts and lists to table
Home-page: https://github.com/saravanabalagi/mdprint
Author: Saravanabalagi Ramachandran
Author-email: saravanabalagi@hotmail.com
License: MIT
Platform: UNKNOWN
Classifier: Development Status :: 4 - Beta
Classifier: Topic :: Software Development :: Libraries
Classifier: License :: OSI Approved :: MIT License
Classifier: Programming Language :: Python :: 3
Classifier: Programming Language :: Python :: 3.6
Classifier: Programming Language :: Python :: 3.7
